{
  "channel": "stable",
  "supervisor": "140",
  "homeassistant": {
    "default": "0.83.0",
    "qemux86": "0.83.0",
    "qemux86-64": "0.83.0",
    "qemuarm": "0.83.0",
    "qemuarm-64": "0.83.0",
    "intel-nuc": "0.83.0",
    "raspberrypi": "0.83.0",
    "raspberrypi2": "0.83.0",
    "raspberrypi3": "0.83.0",
    "raspberrypi3-64": "0.83.0",
    "tinker": "0.83.0",
    "odroid-c2": "0.83.0",
    "odroid-xu": "0.83.0"
  },
  "hassos": {
    "ova": "1.13",
    "rpi": "1.13",
    "rpi0-w": "1.13",
    "rpi2": "1.13",
    "rpi3": "1.13",
    "rpi3-64": "1.13",
    "tinker": "2.3",
    "odroid-c2": "2.3"
  },
  "hassos-cli": "7"
}
